Metadata-Version: 2.1
Name: planetary-datasets
Version: 0.0.1
Summary: Datasets for ML models for planetary use-cases (e.g. solar mapping, land use, forecasting)
Home-page: https://github.com/jacobbieker/planetary-datasets
Author: Jacob Bieker
Author-email: jacob@bieker.tech
License: UNKNOWN
Platform: UNKNOWN
License-File: LICENSE
